{
  "name": "FORAGER",
  "description": "You eat fruit, honey, roots, and raw meat.",
  "type": "origins:prevent_item_use",
  "item_condition": {
    "type": "origins:and",
    "conditions": [
      {
        "type": "origins:food"
      },
      {
        "type": "origins:ingredient",
        "ingredient": {
          "tag": "halfstackorigins:alwayseat"
        },
        "inverted": true
      },
      {
        "type": "origins:ingredient",
        "ingredient": {
          "tag": "halfstackorigins:fruit"
        },
        "inverted": true
      },
      {
        "type": "origins:ingredient",
        "ingredient": {
          "tag": "halfstackorigins:roots"
        },
        "inverted": true
      },
      {
        "type": "origins:ingredient",
        "ingredient": {
          "tag": "halfstackorigins:grass"
        },
        "inverted": true
      },
      {
        "type": "origins:ingredient",
        "ingredient": {
          "tag": "halfstackorigins:raw_meat"
        },
        "inverted": true
      },
      {
        "type": "origins:ingredient",
        "ingredient": {
          "item": "minecraft:tadpole_bucket"
        },
        "inverted": true
      }
    ]
  }
}